indico_toolkit/__init__.py
indico_toolkit/association/__init__.py
indico_toolkit/association/association.py
indico_toolkit/association/extracted_tokens.py
indico_toolkit/association/line_items.py
indico_toolkit/association/positioning.py
indico_toolkit/association/splitting.py
indico_toolkit/auto_review/__init__.py
indico_toolkit/auto_review/auto_review_functions.py
indico_toolkit/auto_review/auto_reviewer.py
indico_toolkit/client.py
indico_toolkit/errors.py
indico_toolkit/etloutput/__init__.py
indico_toolkit/etloutput/box.py
indico_toolkit/etloutput/cell.py
indico_toolkit/etloutput/etloutput.py
indico_toolkit/etloutput/range.py
indico_toolkit/etloutput/span.py
indico_toolkit/etloutput/table.py
indico_toolkit/etloutput/token.py
indico_toolkit/etloutput/utils.py
indico_toolkit/indico_wrapper/__init__.py
indico_toolkit/indico_wrapper/download.py
indico_toolkit/indico_wrapper/indico_wrapper.py
indico_toolkit/indico_wrapper/modelop.py
indico_toolkit/indico_wrapper/workflow.py
indico_toolkit/metrics/__init__.py
indico_toolkit/metrics/compare_ground_truth.py
indico_toolkit/metrics/compare_models.py
indico_toolkit/metrics/metrics.py
indico_toolkit/metrics/plotting.py
indico_toolkit/ocr/__init__.py
indico_toolkit/ocr/ondoc_object.py
indico_toolkit/ocr/standard_object.py
indico_toolkit/pipelines/__init__.py
indico_toolkit/pipelines/file_processing.py
indico_toolkit/polling/__init__.py
indico_toolkit/polling/autoreview.py
indico_toolkit/polling/downstream.py
indico_toolkit/polling/queries.py
indico_toolkit/py.typed
indico_toolkit/results/__init__.py
indico_toolkit/results/document.py
indico_toolkit/results/normalization.py
indico_toolkit/results/predictionlist.py
indico_toolkit/results/predictions/__init__.py
indico_toolkit/results/predictions/citation.py
indico_toolkit/results/predictions/classification.py
indico_toolkit/results/predictions/documentextraction.py
indico_toolkit/results/predictions/extraction.py
indico_toolkit/results/predictions/formextraction.py
indico_toolkit-7.2.2.dist-info/LICENSE
indico_toolkit-7.2.2.dist-info/METADATA
indico_toolkit-7.2.2.dist-info/WHEEL
indico_toolkit-7.2.2.dist-info/RECORD
