Metadata-Version: 2.3
Name: indico-toolkit
Version: 7.2.2
Summary: Classes, functions, and abstractions for Indico IPA
License: MIT
Author: Indico Solutions Engineering
Author-email: solutionsengineering@indicodata.ai
Requires-Python: >=3.10
Classifier: License :: OSI Approved :: MIT License
Classifier: Programming Language :: Python :: 3
Classifier: Programming Language :: Python :: 3.10
Classifier: Programming Language :: Python :: 3.11
Classifier: Programming Language :: Python :: 3.12
Classifier: Programming Language :: Python :: 3.13
Provides-Extra: all
Provides-Extra: downloads
Provides-Extra: examples
Provides-Extra: metrics
Provides-Extra: predictions
Provides-Extra: snapshots
Requires-Dist: indico-client (>=6.14.0,<7.0.0)
Requires-Dist: pandas (>=2.2.3,<3.0.0) ; extra == "all"
Requires-Dist: pandas (>=2.2.3,<3.0.0) ; extra == "downloads"
Requires-Dist: pandas (>=2.2.3,<3.0.0) ; extra == "examples"
Requires-Dist: pandas (>=2.2.3,<3.0.0) ; extra == "metrics"
Requires-Dist: pandas (>=2.2.3,<3.0.0) ; extra == "predictions"
Requires-Dist: pandas (>=2.2.3,<3.0.0) ; extra == "snapshots"
Requires-Dist: plotly (>=5.2.1,<6.0.0) ; extra == "all"
Requires-Dist: plotly (>=5.2.1,<6.0.0) ; extra == "metrics"
Requires-Dist: tqdm (>=4.50.0,<5.0.0) ; extra == "all"
Requires-Dist: tqdm (>=4.50.0,<5.0.0) ; extra == "downloads"
Project-URL: source, https://github.com/IndicoDataSolutions/Indico-Solutions-Toolkit
